exec.v
module exec(rs_index,rs1_data,rs2_data,func,rob_ind,clk1,clk2,rd,exec_b);
input [7:0]rs1_data;
input [7:0]rs2_data;
input [3:0]func,rd;
input [2:0]rob_ind,rs_index;
input clk1,clk2,exec_b;
integer count_as;
integer count_md;
reg[15:0] out1;
always @(posedge clk2)
begin
    $display("\nExecution stage : \n");
    $display("exec: rob_ind = %b, rd = %b",rob_ind,rd);
    if (exec_b == 1)
    begin
        count_as = 0;
        count_md = 0;
        case(func)
            4'b0000:
            begin
                out1 <= rs1_data+rs2_data;
                count_as <= 1;
                tomasulo.pr3_addexec <= 0;
                tomasulo.ROB[rob_ind][2] =  out1;
                tomasulo.regbank[rd][1] = 8;
            end
            4'b0001:
            begin
                out1 <= #20 rs1_data - rs2_data;
                count_as <= #20 1;
                tomasulo.pr3_addexec <= #20 0;
                tomasulo.ROB[rob_ind][2] = #20 out1;
                tomasulo.regbank[rd][1] = #20 8;
            end
            4'b0010:
            begin
                out1 <= #40 rs1_data*rs2_data;
                count_md <= #40 1;
                tomasulo.pr3_mulexec <= #40 0;
                tomasulo.ROB[rob_ind][2] = #40 out1;
                tomasulo.regbank[rd][1] = #40 8;
            end
                4'b0011:
            begin
                out1 <= #60 rs1_data/rs2_data;
                count_md <= #60 1;
                tomasulo.pr3_mulexec <= #60 0;
                tomasulo.ROB[rob_ind][2] <= #60 out1;
                tomasulo.regbank[rd][1] <= #60 8;
            end
            4'b0100:
            begin
                //out1 <= tomasulo.memory[rs1_data+rs2_data];
                //count <= 1;
            end
            4'b0101:
            begin
                //tomasulo.memory[rs1_data+rs2_data] <= tomasulo.regbank[rd][0];
                //count <= 1;
            end
            //4'b0110: out =
        endcase
    end
    $display("rs1_data = %b, rs2_data = %b, funct = %b, rob_ind = %b, exec_b = %b,out = %b",rs1_data,rs2_data,func,rob_ind,exec_b,out1);
    $display("Values of rob and regbank for r3 = %b and %b",tomasulo.ROB[0][2],tomasulo.regbank[3][1]);
end

endmodule

RS.v

module Rstation_append(rs1_b,rs2_b,rs1,rs2,rob_ind,func,clk1,clk2,rd,count);

//These 2 bits are two check if the registers are available or not
input rs1_b,rs2_b,count;
input[3:0] rs1,rs2,func,rd;
input [2:0] rob_ind;
// input [7:0] addr;
input clk1,clk2;
integer temp,temp2,temp3,temp4,temp5;
integer add_index,mul_index;
reg exec_b;
// output [15:0] out;

//RS coulmns: func,rob_rs1,rs1,rob_rs2,rs2,rob,rs1b,rs2b,busy
//if rs1_b is 1 then it is available

always @(posedge clk1)
  begin
      $display("Reservation Station: ");
      for(temp4 = 2; temp4 >= 0; temp4--)
      begin
        if((func == 4'b0000)||(func == 4'b0001)) begin
          if(tomasulo.add_array[temp4][8] == 0) begin
                add_index = temp4;
                // break;
              end
          end
        else if((func == 4'b0010)||(func == 4'b0011)) begin
          if(tomasulo.mul_array[temp4][8] == 0) begin
                mul_index = temp4;
                // break;
              end
          end
      end
      if (count == 1)
      begin
        // $display("Reservation Station: ");
        //This is for add and sub
        if ((func == 4'b0000)||(func == 4'b0001))
        begin
            tomasulo.add_array[add_index][0] <= func;
            tomasulo.add_array[add_index][1+rs1_b] <= rs1;
            tomasulo.add_array[add_index][3+rs2_b] <= rs2;
            tomasulo.add_array[add_index][5] <= rob_ind;
            tomasulo.add_array[add_index][6] <= rs1_b;
            tomasulo.add_array[add_index][7] <= rs2_b;
            tomasulo.add_array[add_index][8] <= 1;
        end
        //This is for multiplication and div
        else if ((func == 4'b0010)||(func == 4'b0011))
        begin
            tomasulo.mul_array[mul_index][0] <= func;
            tomasulo.mul_array[mul_index][1+rs1_b] <= rs1;
            tomasulo.mul_array[mul_index][3+rs2_b] <= rs2;
            tomasulo.mul_array[mul_index][5] <= rob_ind;
            tomasulo.mul_array[mul_index][6] <= rs1_b;
            tomasulo.mul_array[mul_index][7] <= rs2_b;
            tomasulo.mul_array[mul_index][8] <= 1;
        end
        //This is for branch
        else if ((func == 4'b0110)||(func == 4'b0111))
        begin
            tomasulo.add_array[add_index][0] <= func;
            tomasulo.add_array[add_index][1+rs1_b] <= rs1;
            tomasulo.add_array[add_index][3+rs2_b] <= rs2;
            tomasulo.add_array[add_index][5] <= rob_ind;
            tomasulo.add_array[add_index][6] <= rs1_b;
            tomasulo.add_array[add_index][7] <= rs2_b;
        end
        //This is for load and store
        else if ((func == 4'b0100)||(func == 4'b0101))
        begin
            tomasulo.add_array[tomasulo.add_count][0] <= func;
            tomasulo.add_array[tomasulo.add_count][1+rs1_b] <= rs1;
            tomasulo.add_array[tomasulo.add_count][3+rs2_b] <= rs2;
            tomasulo.add_array[tomasulo.add_count][5] <= rob_ind;
            tomasulo.add_array[tomasulo.add_count][6] <= rs1_b;
            tomasulo.add_array[tomasulo.add_count][7] <= rs2_b;
        end
      end
  end

always @(posedge clk1)
  begin
  exec_b <= 0;
    for(temp2 = 0; temp2<3; temp2++)
    begin
    // $display("rs1b = %b rs2_b = %b,add_exec = %b",tomasulo.add_array[temp2][6],tomasulo.add_array[temp2][7],tomasulo.pr3_addexec);
      if((tomasulo.add_array[temp2][6] == 3'b1) && (tomasulo.add_array[temp2][7] == 3'b1) && (tomasulo.pr3_addexec == 0) && (tomasulo.add_array[temp2][8] == 1))
      begin
        tomasulo.pr3_rsindex <= temp2;
        tomasulo.pr3_rs1data <= tomasulo.regbank[tomasulo.add_array[temp2][2]][0];
        tomasulo.pr3_rs2data <= tomasulo.regbank[tomasulo.add_array[temp2][4]][0];
        tomasulo.pr3_func <=  tomasulo.add_array[temp2][0];
        tomasulo.pr3_rob_ind <= tomasulo.add_array[temp2][5];
        tomasulo.pr3_rd <= tomasulo.ROB[tomasulo.add_array[temp2][5]][1];
        exec_b <= 1;
        tomasulo.pr3_addexec += 1;
      end
    end
    for(temp3 = 0; temp3 < 3; temp3++)
    begin
    // $display("rs1b = %b rs2_b = %b,mul_exec = %b",tomasulo.mul_array[temp3][6],tomasulo.mul_array[temp3][7],tomasulo.pr3_mulexec);
      // $display("reg_value = %b",tomasulo.regbank[tomasulo.add_array[temp3][2]][0]);
      if((tomasulo.mul_array[temp3][6] == 3'b1) && (tomasulo.mul_array[temp3][7] == 3'b1) && (tomasulo.pr3_mulexec == 0) && (exec_b == 0) && (tomasulo.mul_array[temp3][8] == 1))
      begin
        tomasulo.pr3_rsindex <= temp3;
        tomasulo.pr3_rs1data <= tomasulo.regbank[tomasulo.mul_array[temp3][2]][0];
        tomasulo.pr3_rs2data <= tomasulo.regbank[tomasulo.mul_array[temp3][4]][0];
        tomasulo.pr3_func <=  tomasulo.mul_array[temp3][0];
        tomasulo.pr3_rob_ind = tomasulo.mul_array[temp3][5];
        tomasulo.pr3_rd <= tomasulo.ROB[tomasulo.mul_array[temp3][5]][1];
        exec_b <= 1;
        tomasulo.pr3_mulexec += 1;
      end
    end
  // checking the first column of RS
  // #100
  // $display("rs1d = %b,rs2d = %b,func = %b,exec_b = %b",tomasulo.pr3_rs1data,tomasulo.pr3_rs2data,tomasulo.pr3_func,exec_b);
  // for(temp = 0;temp < 2;temp++)
  //   $display("rs1b = %b rs2_b = %b,add_exec = %b",tomasulo.mul_array[temp][6],tomasulo.mul_array[temp][7],tomasulo.pr3_mulexec);
  // for(temp = 0;temp < 2;temp++)
  //   $display("rs1b = %b rs2_b = %b,add_exec = %b",tomasulo.add_array[temp][6],tomasulo.add_array[temp][7],tomasulo.pr3_addexec);

  end

exec ex(tomasulo.pr3_rsindex,tomasulo.pr3_rs1data,tomasulo.pr3_rs2data,tomasulo.pr3_func,tomasulo.pr3_rob_ind,clk1,clk2,tomasulo.pr3_rd,exec_b);
// always@(posedge clk2)
// begin
// for(i = 0;i < 16;i++)
//     $display("rob_val = %b",tomasulo.regbank[i][1]);
// end
endmodule

issue.v
module issue (rs1, rs2, rd, func,clk1, clk2);
//Initialized the registers 
input [3:0] rs1, rs2, rd, func;
wire [3:0] rs1_data,rs2_data;
input clk1, clk2;
output reg [15:0] Zout;
// reg count;
// reg [2:0] tomasulo.pr2_rob_ind;
// reg rs1_b,rs2_b;
always @(posedge clk2)
begin
    tomasulo.pr2_count = 0;
    $display("\nIssue stage :\n ");
    // $display("rs1 = %b,rs2 = %b,func = %b",rs1,rs2,func);
    if(tomasulo.regbank[rs1][1] < 16'b1000)
        tomasulo.pr2_rs1b = 0;
    else
        tomasulo.pr2_rs1b = 1;
    if(tomasulo.regbank[rs2][1] < 16'b1000)
        tomasulo.pr2_rs2b = 0;
    else
        tomasulo.pr2_rs2b = 1;
//Check condition if ROB is full or not
    if (tomasulo.tail_p - tomasulo.head_p == 7)
    begin
        if (tomasulo.tail_p == 7)
        begin
            if(tomasulo.add_count < 3)
                tomasulo.pr2_count   =  1;
            else if(tomasulo.mul_count < 3)
                tomasulo.pr2_count = 1;
            else if(tomasulo.bch_count < 3)
                tomasulo.pr2_count = 1;
            // else
                //stall
        end
    end
    else if(tomasulo.tail_p - tomasulo.head_p < 7)
    begin
        if (tomasulo.tail_p == 7)
        begin
            if(tomasulo.add_count < 3)
                tomasulo.pr2_count = 1;
            else if(tomasulo.mul_count < 3)
                tomasulo.pr2_count = 1;
            else if(tomasulo.bch_count < 3)
                tomasulo.pr2_count = 1;
            // else
                //stall
        end
        else
        begin
            if(tomasulo.add_count < 3)
                tomasulo.pr2_count = 1;
            else if(tomasulo.mul_count < 3)
                tomasulo.pr2_count = 1;
            else if(tomasulo.bch_count < 3)
                tomasulo.pr2_count = 1;
            // else
                //stall
        end
    end
    else
    begin
        if(tomasulo.add_count < 3)
            tomasulo.pr2_count = 1;
        else if(tomasulo.mul_count < 3)
            tomasulo.pr2_count = 1;
        else if(tomasulo.bch_count < 3)
        begin
            tomasulo.pr2_count = 1;
        end
        // else
            //stall
    end

    if (tomasulo.pr2_count == 1)
    begin
    // $display("rs1_b = %b,rs2_b = %b,func = %b",tomasulo.pr2_rs1b,tomasulo.pr2_rs2b,func);
        tomasulo.ROB[tomasulo.tail_p][0] = func;
        tomasulo.ROB[tomasulo.tail_p][1] = rd;
        tomasulo.regbank[rd][1] = tomasulo.tail_p;
        tomasulo.pr2_rob_ind = tomasulo.tail_p;
        tomasulo.tail_p = tomasulo.tail_p + 1;
        if((func == 4'b0000) || (func == 4'b0001))
            tomasulo.add_count += 1;
        if((func == 4'b0010) || (func == 4'b0011))
            tomasulo.mul_count += 1;
    end
    if(tomasulo.pr2_rs1b == 0)
      tomasulo.pr2_rs1 = tomasulo.regbank[rs1][1];
    else
      tomasulo.pr2_rs1 = rs1;
    if(tomasulo.pr2_rs2b == 0)
      tomasulo.pr2_rs2 = tomasulo.regbank[rs2][1];
    else
      tomasulo.pr2_rs2 = rs2   ;
    tomasulo.pr2_func = func;
    tomasulo.pr2_rd = rd;

    $display("rs1b,rs2b,rs1,rs2,rob_ind,func,clk1,clk2,rd,count");
    $display("%b\t%b\t%b\t%b\t%b",tomasulo.pr2_rs1b,tomasulo.pr2_rs2b,tomasulo.pr2_rs1,tomasulo.pr2_rs2,tomasulo.pr2_rob_ind);
    $display("%b\t%b\t%b\t%b\t%b",tomasulo.pr2_func,clk1,clk2,tomasulo.pr2_rd,tomasulo.pr2_count);
end

Rstation_append rs(tomasulo.pr2_rs1b,tomasulo.pr2_rs2b,tomasulo.pr2_rs1,tomasulo.pr2_rs2,tomasulo.pr2_rob_ind,tomasulo.pr2_func,clk1,clk2,tomasulo.pr2_rd,tomasulo.pr2_count);

endmodule

instruction_set.v
//This is the instruction set which takes the PC number and gives the instruction in that memory.

module instruction_set(PC,clk1,output_instruction);

input [3:0] PC;
input clk1;
output reg [15:0] output_instruction;
integer num;

//These are the instructions that we use for matrix multiplication.

initial begin
    //mul r3 r1 r2
    //add r5 r3 r4
    //add r7 r2 r6
    //add r10 r8 r9
    //mul r11 r7 r10
    //sub r6 r11 r5    0001101101010110

    tomasulo.memory[0] = 16'b0010000100100011;
    tomasulo.memory[1] = 16'b0000001101000101;
    tomasulo.memory[2] = 16'b0000001001100111;
    tomasulo.memory[3] = 16'b0000100010011010;
    tomasulo.memory[4] = 16'b0010011110101011;
    tomasulo.memory[5] = 16'b0001101101010110;
end

always@(posedge clk1)
  begin
    num = PC;
    output_instruction = tomasulo.memory[num];  //Here we are assigning the instruction present in the memory.
  end


endmodule

Tomasulo.v
//Instructions that are defined

// add = 0000
// sub = 0001
// mul = 0010
// div = 0011
// load = 0100
// store = 0101
// beq = 0110
// bneq = 0111
//Ins format = func,rs1,rs2,rd
//for branches, imm[3:0] = rd
//for ld,store, func,rs1+ s2 - base address,rd


module tomasulo(pc,clk1,clk2);

  input[3:0] pc;
  input clk1,clk2;

  wire [15:0] inst; //This is for getting instruction from ins set
  // reg [3:0] rs1,rs2,func,rd;

  //These are stage 1 pr
  reg [3:0] pr1_rs1,pr1_rs2,pr1_func,pr1_rd;
  reg pr2_rs1b,pr2_rs2b,pr2_count;
  //These are stage 2 pr
  reg [3:0] pr2_rs1,pr2_rs2,pr2_func,pr2_rd;
  reg[2:0] pr2_rob_ind;
  //These are stage3 pr
  reg pr3_addexec,pr3_mulexec;
  reg [7:0] pr3_rs1data,pr3_rs2data;
  reg [3:0] pr3_func,pr3_rd;
  reg [2:0] pr3_rob_ind,pr3_rsindex;


  integer add_count,mul_count,bch_count;
  reg [2:0] head_p,tail_p;
  reg [3:0] add_array[0:2][0:8]; //RS add and sub
  reg [3:0] mul_array[0:2][0:8]; //RS mul_array
  reg [4:0] bch_array[0:1][0:8]; //RS branches
  reg [15:0] ls_queue[0:3][0:2]; //Each index should be 16 bits since we wil be storing the data
  reg [15:0] regbank[0:15][0:1]; //First column is actual value and second column is ROB
  reg [15:0] ROB[0:7][0:2];  //Each index should be 16 bits since we will be storing the data
  reg [15:0] memory[0:255]; //Memory


instruction_set k1(pc,clk1,inst);

always @(inst)
  begin
  $display("In fetch stage:");
  pr1_func = inst[15:12];
  pr1_rs1 = inst[11:8];
  pr1_rs2 = inst[7:4];
  pr1_rd = inst[3:0];
  $display("values of pc = %b,values of func = %b,values of rs1 = %b,values of rs2 = %b,values of rd = %b",pc,pr1_func,pr1_rs1,pr1_rs2,pr1_rd);
end

issue is1(pr1_rs1, pr1_rs2, pr1_rd, pr1_func,clk1, clk2);

endmodule

Tomasulo_tb.v

module tomasulo_tb;

reg[3:0] pc;
reg clk1,clk2;
integer  k;
integer clock_cycle;

tomasulo tomas(
.pc(pc),
.clk1(clk1),
.clk2(clk2)
);

initial begin
  $dumpfile("tomasulo_tb.vcd");
  $dumpvars(0,tomasulo_tb);
  clk1 = 0; clk2 = 0; pc = 0;
  clock_cycle = 1;
  repeat(20)
    begin
      #5 clk1 = 1; #5 clk1 = 0;
      #5 clk2 = 1; #5 clk2 = 0;
      $display("\nCLOCK CYCLE : %d\n",clock_cycle);
      clock_cycle += 1;
    end
end

//Initialising all the registers
initial begin
  for(k = 0;k < 16; k++)
      tomas.regbank[k][0] = k;
  for(k = 0;k < 8;k++)
      tomas.ROB[k][1] = 8;
  for(k = 0;k < 3;k++)
      tomas.add_array[k][8] = 3'b0;
  for(k = 0;k < 3;k++)
      tomas.mul_array[k][8] = 3'b0;
  // for(k = 0; k < 3 ;k++)
      // tomas.bch_array[k][8] = 0;
  tomas.add_count = 0;
  tomas.mul_count = 2'b0;
  tomas.bch_count = 2'b0;
  tomas.head_p = 3'b0;
  tomas.tail_p = 3'b0;
  tomas.pr3_addexec = 0;
  tomas.pr3_mulexec = 0;
end

always @(posedge clk2) begin
    pc += 4'b1;
    end
// initial
//   repeat(6)
//     begin
//       #20 pc = pc + 4'b1;
//     end

endmodule

tomasulo_tb.vcd
$date
	Mon May 18 16:37:43 2020
$end
$version
	Icarus Verilog
$end
$timescale
	1s
$end
$scope module tomasulo_tb $end
$var reg 1 ! clk1 $end
$var reg 1 " clk2 $end
$var reg 4 # pc [3:0] $end
$var integer 32 $ clock_cycle [31:0] $end
$var integer 32 % k [31:0] $end
$scope module tomas $end
$var wire 1 ! clk1 $end
$var wire 1 " clk2 $end
$var wire 4 & pc [3:0] $end
$var wire 16 ' inst [15:0] $end
$var reg 3 ( head_p [2:0] $end
$var reg 4 ) pr1_func [3:0] $end
$var reg 4 * pr1_rd [3:0] $end
$var reg 4 + pr1_rs1 [3:0] $end
$var reg 4 , pr1_rs2 [3:0] $end
$var reg 1 - pr2_count $end
$var reg 4 . pr2_func [3:0] $end
$var reg 4 / pr2_rd [3:0] $end
$var reg 3 0 pr2_rob_ind [2:0] $end
$var reg 4 1 pr2_rs1 [3:0] $end
$var reg 1 2 pr2_rs1b $end
$var reg 4 3 pr2_rs2 [3:0] $end
$var reg 1 4 pr2_rs2b $end
$var reg 1 5 pr3_addexec $end
$var reg 4 6 pr3_func [3:0] $end
$var reg 1 7 pr3_mulexec $end
$var reg 4 8 pr3_rd [3:0] $end
$var reg 3 9 pr3_rob_ind [2:0] $end
$var reg 8 : pr3_rs1data [7:0] $end
$var reg 8 ; pr3_rs2data [7:0] $end
$var reg 3 < pr3_rsindex [2:0] $end
$var reg 3 = tail_p [2:0] $end
$var integer 32 > add_count [31:0] $end
$var integer 32 ? bch_count [31:0] $end
$var integer 32 @ mul_count [31:0] $end
$scope module is1 $end
$var wire 1 ! clk1 $end
$var wire 1 " clk2 $end
$var wire 4 A func [3:0] $end
$var wire 4 B rd [3:0] $end
$var wire 4 C rs1 [3:0] $end
$var wire 4 D rs2 [3:0] $end
$var reg 16 E Zout [15:0] $end
$scope module rs $end
$var wire 1 ! clk1 $end
$var wire 1 " clk2 $end
$var wire 1 - count $end
$var wire 4 F func [3:0] $end
$var wire 4 G rd [3:0] $end
$var wire 3 H rob_ind [2:0] $end
$var wire 4 I rs1 [3:0] $end
$var wire 1 2 rs1_b $end
$var wire 4 J rs2 [3:0] $end
$var wire 1 4 rs2_b $end
$var reg 1 K exec_b $end
$var integer 32 L add_index [31:0] $end
$var integer 32 M mul_index [31:0] $end
$var integer 32 N temp2 [31:0] $end
$var integer 32 O temp3 [31:0] $end
$var integer 32 P temp4 [31:0] $end
$scope module ex $end
$var wire 1 ! clk1 $end
$var wire 1 " clk2 $end
$var wire 1 K exec_b $end
$var wire 4 Q func [3:0] $end
$var wire 4 R rd [3:0] $end
$var wire 3 S rob_ind [2:0] $end
$var wire 8 T rs1_data [7:0] $end
$var wire 8 U rs2_data [7:0] $end
$var wire 3 V rs_index [2:0] $end
$var reg 16 W out1 [15:0] $end
$var integer 32 X count_as [31:0] $end
$var integer 32 Y count_md [31:0] $end
$upscope $end
$upscope $end
$upscope $end
$scope module k1 $end
$var wire 4 Z PC [3:0] $end
$var wire 1 ! clk1 $end
$var reg 16 [ output_instruction [15:0] $end
$var integer 32 \ num [31:0] $end
$upscope $end
$upscope $end
$upscope $end
$enddefinitions $end
#0
$dumpvars
bx \
bx [
b0 Z
bx Y
bx X
bx W
bx V
bx U
bx T
bx S
bx R
bx Q
bx P
bx O
bx N
bx M
bx L
xK
bx J
bx I
bx H
bx G
bx F
bx E
bx D
bx C
bx B
bx A
b0 @
b0 ?
b0 >
b0 =
bx <
bx ;
bx :
bx 9
bx 8
07
bx 6
05
x4
bx 3
x2
bx 1
bx 0
bx /
bx .
x-
bx ,
bx +
bx *
bx )
b0 (
bx '
b0 &
b11 %
b1 $
b0 #
0"
0!
$end
#5
0K
b11 *
b11 B
b10 ,
b10 D
b1 +
b1 C
b10 )
b10 A
b10000100100011 '
b10000100100011 [
b0 \
b11111111111111111111111111111111 P
b11 O
b11 N
1!
#10
0!
#15
b11 /
b11 G
b10 .
b10 F
b10 3
b10 J
b1 1
b1 I
b1 @
b1 =
b0 0
b0 H
14
12
1-
b1 #
b1 &
b1 Z
1"
#20
b10 $
0"
#25
b101 *
b101 B
b100 ,
b100 D
b11 +
b11 C
b0 )
b0 A
b11 O
b11 N
b0 M
b11111111111111111111111111111111 P
b1101000101 '
b1101000101 [
b1 \
1!
#30
0!
#35
b10 #
b10 &
b10 Z
b101 /
b101 G
b0 .
b0 F
b100 3
b100 J
b0 1
b0 I
b1 >
b10 =
b1 0
b1 H
02
1-
1"
#40
b11 $
0"
#45
1K
b11 8
b11 R
b10 6
b10 Q
b10 ;
b10 U
b1 :
b1 T
b0 <
b0 V
b111 *
b111 B
b110 ,
b110 D
b10 +
b10 C
b1001100111 '
b1001100111 [
b10 \
b0 L
b11111111111111111111111111111111 P
17
b0 9
b0 S
b11 O
b11 N
1!
#50
0!
#55
07
b10 W
b1 Y
b0 X
b111 /
b111 G
b110 3
b110 J
b10 1
b10 I
b10 >
b11 =
b10 0
b10 H
12
1-
b11 #
b11 &
b11 Z
1"
#60
b100 $
0"
#65
0K
b1010 *
b1010 B
b1001 ,
b1001 D
b1000 +
b1000 C
b11 O
b11 N
b1 L
b11111111111111111111111111111111 P
b100010011010 '
b100010011010 [
b11 \
1!
#70
0!
#75
b100 #
b100 &
b100 Z
b1010 /
b1010 G
b1001 3
b1001 J
b1000 1
b1000 I
b11 >
b100 =
b11 0
b11 H
1-
1"
#80
b101 $
0"
#85
1K
b111 8
b111 R
b10 9
b10 S
b0 6
b0 Q
b110 ;
b110 U
b10 :
b10 T
b1 <
b1 V
b1011 *
b1011 B
b1010 ,
b1010 D
b111 +
b111 C
b10 )
b10 A
b10011110101011 '
b10011110101011 [
b100 \
b10 L
b11111111111111111111111111111111 P
b11 O
15
b11 N
1!
#90
0!
#95
05
b1 X
b1000 W
b0 Y
b1011 /
b1011 G
b10 .
b10 F
b11 3
b11 J
b10 1
b10 I
b10 @
b101 =
b100 0
b100 H
04
02
1-
b101 #
b101 &
b101 Z
1"
#100
b110 $
0"
#105
b1010 8
b1010 R
b11 9
b11 S
b1001 ;
b1001 U
b1000 :
b1000 T
b10 <
b10 V
1K
b101 *
b101 B
b1011 ,
b1011 D
b101 +
b101 C
b1 )
b1 A
b11 O
15
b11 N
b0 M
b11111111111111111111111111111111 P
b1010110110101 '
b1010110110101 [
b101 \
1!
#110
0!
#115
b110 #
b110 &
b110 Z
b101 /
b101 G
b1 .
b1 F
b100 3
b100 J
b101 1
b101 I
b100 >
b110 =
b101 0
b101 H
1-
05
b10001 W
b1 X
1"
#120
b111 $
0"
#125
0K
bx *
bx B
bx ,
bx D
bx +
bx C
bx )
bx A
bx '
bx [
b110 \
b1 L
b11111111111111111111111111111111 P
b11 O
b11 N
1!
#130
0!
#135
bx /
bx G
bx .
bx F
bx 3
bx J
bx 1
bx I
b111 =
b110 0
b110 H
14
12
1-
b111 #
b111 &
b111 Z
1"
#140
b1000 $
0"
#145
b11 O
b11 N
b11111111111111111111111111111111 P
b111 \
1!
#150
0!
#155
b1000 #
b1000 &
b1000 Z
b0 =
b111 0
b111 H
1-
1"
#160
b1001 $
0"
#165
b1000 \
b11111111111111111111111111111111 P
b11 O
b11 N
1!
#170
0!
#175
b1 =
b0 0
b0 H
1-
b1001 #
b1001 &
b1001 Z
1"
#180
b1010 $
0"
#185
b11 O
b11 N
b11111111111111111111111111111111 P
b1001 \
1!
#190
0!
#195
b1010 #
b1010 &
b1010 Z
b10 =
b1 0
b1 H
1-
1"
#200
b1011 $
0"
#205
b1010 \
b11111111111111111111111111111111 P
b11 O
b11 N
1!
#210
0!
#215
b11 =
b10 0
b10 H
1-
b1011 #
b1011 &
b1011 Z
1"
#220
b1100 $
0"
#225
b11 O
b11 N
b11111111111111111111111111111111 P
b1011 \
1!
#230
0!
#235
b1100 #
b1100 &
b1100 Z
b100 =
b11 0
b11 H
1-
1"
#240
b1101 $
0"
