instruction_set.v
//This is the instruction set which takes the PC number and gives the instruction in that memory.

module instruction_set(PC,clk1,output_instruction);

input [3:0] PC;
input clk1;
output reg [15:0] output_instruction;
integer num;

//These are the instructions that we use for matrix multiplication.

initial begin
    //mul r3 r1 r2
    //add r5 r3 r4
    //add r7 r2 r6
    //add r10 r8 r9
    //mul r11 r7 r10
    //sub r6 r11 r5    0001101101010110

    tomasulo.memory[0] = 16'b0010000100100011;
    tomasulo.memory[1] = 16'b0000001101000101;
    tomasulo.memory[2] = 16'b0000001001100111;
    tomasulo.memory[3] = 16'b0000100010011010;
    tomasulo.memory[4] = 16'b0010011110101011;
    tomasulo.memory[5] = 16'b0001101101010110;
end

always@(posedge clk1)
  begin
    num = PC;
    output_instruction = tomasulo.memory[num];  //Here we are assigning the instruction present in the memory.
  end


endmodule

Tomasulo.v
module tomasulo(pc,clk1,clk2);

  input[3:0] pc;
  input clk1,clk2;

  wire [15:0] inst; //This is for getting instruction from ins set
  reg [3:0] rs1,rs2,func,rd;
  reg [1:0] add_count,mul_count,bch_count;
  reg [2:0] head_p,tail_p;
  reg [3:0] add_array[0:2][0:5]; //RS add and sub
  reg [3:0] mul_array[0:2][0:5]; //RS mul_array
  reg [4:0] bch_array[0:1][0:2]; //RS branches
  reg [15:0] ls_queue[0:3][0:2]; //Each index should be 16 bits since we wil be storing the data
  reg [15:0] regbank[0:15]; //First column is actual value and second column is ROB
  reg [15:0] ROB[0:7][0:2];  //Each index should be 16 bits since we will be storing the data
  reg [15:0] memory[0:255]; //Memory


instruction_set k1(pc,clk1,inst);

initial begin
  #10;
  func = inst[15:12];
  rs1 = inst[11:8];
  rs2 = inst[7:4];
  rd = inst[3:0];
  $display("values of func = %b",func);
  $display("values of rs1 = %b",rs1);
  $display("values of rs2 = %b",rs2);
  $display("values of rd = %b",rd);
end

endmodule

//
// module pipeline(out,rs1,rs2,rd,func,addr,clk1,clk2);
//
//       input [4:0] rs1,rs2,rd,func;
//       input [7:0] addr;
//       input clk1,clk2;
//       output [15:0] out;
//
//       reg [15:0]


//Instructions that are defined

// add = 0000
// sub = 0001
// mul = 0010
// div = 0011
// load = 0100
// store = 0101
// beq = 0110
// bneq = 0111
//Ins format = func,rs1,rs2,rd
//for branches, imm[3:0] = rd
//for ld,store, func,main_addr,rd

Tomasulo_tb.v

module tomasulo_tb;

reg[3:0] pc;
reg clk1,clk2;
integer  k;

 tomasulo tomas(
  .pc(pc),
  .clk1(clk1),
  .clk2(clk2)
  );

initial begin
  $dumpfile("tomasulo_tb.vcd");
  $dumpvars(0,tomasulo_tb);
  clk1 = 0; clk2 = 0; pc = 0;
  repeat(20)
    begin
      #5 clk1 = 1; #5 clk2 = 0;
      #5 clk2 = 1; #5 clk2 = 0;
    end
end

//Initialising all the registers
initial begin
  for(k = 0;k < 16; k++)
      tomas.regbank[k] = k;
end

initial
  repeat(8)
    begin
      #20 pc += 4'b1;
    end

endmodule

tomasulo_tb.vcd
$date
	Sun May 17 12:30:35 2020
$end
$version
	Icarus Verilog
$end
$timescale
	1s
$end
$scope module tomasulo_tb $end
$var reg 1 ! clk1 $end
$var reg 1 " clk2 $end
$var reg 4 # pc [3:0] $end
$var integer 32 $ k [31:0] $end
$scope module tomas $end
$var wire 1 ! clk1 $end
$var wire 1 " clk2 $end
$var wire 4 % pc [3:0] $end
$var wire 16 & inst [15:0] $end
$var reg 4 ' func [3:0] $end
$var reg 4 ( rd [3:0] $end
$var reg 4 ) rs1 [3:0] $end
$var reg 4 * rs2 [3:0] $end
$scope module k1 $end
$var wire 4 + PC [3:0] $end
$var wire 1 ! clk1 $end
$var reg 16 , output_instruction [15:0] $end
$var integer 32 - num [31:0] $end
$upscope $end
$upscope $end
$upscope $end
$enddefinitions $end
#0
$dumpvars
bx -
bx ,
b0 +
bx *
bx )
bx (
bx '
bx &
b0 %
b10000 $
b0 #
0"
0!
$end
#5
b10000100100011 &
b10000100100011 ,
b0 -
1!
#10
b11 (
b10 *
b1 )
b10 '
#15
1"
#20
0"
b1 #
b1 %
b1 +
#35
1"
#40
0"
b10 #
b10 %
b10 +
#55
1"
#60
0"
b11 #
b11 %
b11 +
#75
1"
#80
0"
b100 #
b100 %
b100 +
#95
1"
#100
0"
b101 #
b101 %
b101 +
#115
1"
#120
0"
b110 #
b110 %
b110 +
#135
1"
#140
0"
b111 #
b111 %
b111 +
#155
1"
#160
0"
b1000 #
b1000 %
b1000 +
